scope_client/__init__.py
scope_client/api_bindings/__init__.py
scope_client/api_bindings/api_client.py
scope_client/api_bindings/api_response.py
scope_client/api_bindings/configuration.py
scope_client/api_bindings/exceptions.py
scope_client/api_bindings/rest.py
scope_client/api_bindings/api/__init__.py
scope_client/api_bindings/api/alert_rules_v1_api.py
scope_client/api_bindings/api/alerts_v1_api.py
scope_client/api_bindings/api/authorization_v1_api.py
scope_client/api_bindings/api/connector_schemas_v1_api.py
scope_client/api_bindings/api/connectors_v1_api.py
scope_client/api_bindings/api/data_plane_associations_v1_api.py
scope_client/api_bindings/api/data_planes_v1_api.py
scope_client/api_bindings/api/data_retrieval_v1_api.py
scope_client/api_bindings/api/datasets_v1_api.py
scope_client/api_bindings/api/default_api.py
scope_client/api_bindings/api/feature_flags_v1_api.py
scope_client/api_bindings/api/groups_v1_api.py
scope_client/api_bindings/api/jobs_v1_api.py
scope_client/api_bindings/api/metric_functions_v1_api.py
scope_client/api_bindings/api/metrics_v1_api.py
scope_client/api_bindings/api/models_v1_api.py
scope_client/api_bindings/api/o_auth_v1_api.py
scope_client/api_bindings/api/organizations_v1_api.py
scope_client/api_bindings/api/projects_v1_api.py
scope_client/api_bindings/api/registration_v1_api.py
scope_client/api_bindings/api/roles_v1_api.py
scope_client/api_bindings/api/tasks_v1_api.py
scope_client/api_bindings/api/upsolve_v1_api.py
scope_client/api_bindings/api/users_v1_api.py
scope_client/api_bindings/api/webhooks_v1_api.py
scope_client/api_bindings/api/workspaces_v1_api.py
scope_client/api_bindings/models/__init__.py
scope_client/api_bindings/models/aggregation_metric_type.py
scope_client/api_bindings/models/aggregation_spec.py
scope_client/api_bindings/models/aggregation_spec_schema.py
scope_client/api_bindings/models/aggregation_spec_schema_init_args_inner.py
scope_client/api_bindings/models/alert.py
scope_client-1.4.1184.dist-info/METADATA
scope_client-1.4.1184.dist-info/WHEEL
scope_client-1.4.1184.dist-info/top_level.txt
scope_client-1.4.1184.dist-info/RECORD
